kocr/__init__.py
kocr/api_server.py
kocr/app/__init__.py
kocr/app/client/__init__.py
kocr/app/client/classes/OcrClient.py
kocr/app/client/classes/__init__.py
kocr/app/ocr/__init__.py
kocr/app/ocr/classes/BaseOcrer.py
kocr/app/ocr/classes/ImageOcrer.py
kocr/app/ocr/classes/OcrEngineConfig.py
kocr/app/ocr/classes/PdfOcrer.py
kocr/app/ocr/classes/__init__.py
kocr/app/ocr/utils/__init__.py
kocr/app/ocr/utils/utils.py
test/__init__.py
test/client_image_test.py
test/client_pdf_test.py
test/client_slice_test.py
kocr-0.1.4.dist-info/METADATA
kocr-0.1.4.dist-info/WHEEL
kocr-0.1.4.dist-info/top_level.txt
kocr-0.1.4.dist-info/RECORD
