Metadata-Version: 2.1
Name: kocr
Version: 0.1.4
Summary: Use to build server end-point and client end-point of OCR service.
Home-page: https://github.com/kime541200/kocr
Author: Kim Chen
Author-email: kime541200@outlook.com
Classifier: Programming Language :: Python :: 3
Classifier: License :: OSI Approved :: MIT License
Classifier: Operating System :: OS Independent
Requires-Python: >=3.9
Requires-Dist: paddlepaddle-gpu
Requires-Dist: paddleocr
Requires-Dist: pdf2image
Requires-Dist: rich
Requires-Dist: python-multipart
Requires-Dist: fastapi
Requires-Dist: uvicorn
Requires-Dist: pydantic
Requires-Dist: opencv-python
